mcp_usee_user/__init__.py
mcp_usee_user/main.py
mcp_usee_user-0.1.3.dist-info/METADATA
mcp_usee_user-0.1.3.dist-info/WHEEL
mcp_usee_user-0.1.3.dist-info/entry_points.txt
mcp_usee_user-0.1.3.dist-info/top_level.txt
mcp_usee_user-0.1.3.dist-info/RECORD
