Metadata-Version: 2.4
Name: mcp-usee-user
Version: 0.1.3
Summary: 测试服务
Requires-Python: >=3.11
Requires-Dist: mcp>=1.6.0
Requires-Dist: httpx>=0.28.1
